<?xml version='1.0' encoding='utf-8'?>
<Jobs>
  <Job id="1105a276-b7de-42b3-9f02-45d9de98fc15" state="Tennesee" district="Clarksville-Mongomery County" districtId="Clarksville-Mongomery County" active="true" lastSeen="2025-10-30T03:23:46+00:00">
    <JobTitle>Assistant Boy's Basketball Coach (100%)-NEMS-*Position available October 2025* (RR-142531)</JobTitle>
    <JobDescription />
    <JobType />
    <Location>Northeast Middle, 3703 Trenton Road, Clarksville, TN 37040</Location>
    <City>Clarksville</City>
    <State>TN</State>
    <Country />
    <ZipCode>37040</ZipCode>
    <Experience />
    <SalaryRange />
    <Benefits />
    <PostingDate>October 2025</PostingDate>
    <ClosingDate />
    <JobUrl>https://jobs.redroverk12.com/org/CMCSS/opening/142531</JobUrl>
    <ApplyUrl>https://jobs.redroverk12.com/org/CMCSS/opening/142531/apply</ApplyUrl>
    <CoachSearchUrl>https://jobs.redroverk12.com/org/CMCSS?search=coach</CoachSearchUrl>
    <EmployerEmail />
    <EmployerFullName>Northeast Middle, 3703 Trenton Road, Clarksville, TN 37040</EmployerFullName>
    <CompanyDescription>Clarksville-Mongomery County coaching jobs</CompanyDescription>
    <CompanyEmail />
    <CompanyName>Clarksville-Mongomery County</CompanyName>
  </Job>
  <Job id="19e9760c-cf0e-42dd-a7bb-447f73e28328" state="Tennesee" district="Clarksville-Mongomery County" districtId="Clarksville-Mongomery County" active="true" lastSeen="2025-10-30T03:24:25+00:00">
    <JobTitle>Assistant Boys Basketball Coach(100%)-CHS-*Position available October 2025* (RR-141744)</JobTitle>
    <JobDescription />
    <JobType />
    <Location>Clarksville High, 151 Richview Road, Clarksville, TN 37043</Location>
    <City>Clarksville</City>
    <State>TN</State>
    <Country />
    <ZipCode>37043</ZipCode>
    <Experience />
    <SalaryRange />
    <Benefits />
    <PostingDate>October 2025</PostingDate>
    <ClosingDate />
    <JobUrl>https://jobs.redroverk12.com/org/CMCSS/opening/141744</JobUrl>
    <ApplyUrl>https://jobs.redroverk12.com/org/CMCSS/opening/141744/apply</ApplyUrl>
    <CoachSearchUrl>https://jobs.redroverk12.com/org/CMCSS?search=coach</CoachSearchUrl>
    <EmployerEmail />
    <EmployerFullName>Clarksville High, 151 Richview Road, Clarksville, TN 37043</EmployerFullName>
    <CompanyDescription>Clarksville-Mongomery County coaching jobs</CompanyDescription>
    <CompanyEmail />
    <CompanyName>Clarksville-Mongomery County</CompanyName>
  </Job>
  <Job id="ed5759cc-6fd8-4312-bf99-53085f5ebaf6" state="Tennesee" district="Maury County" districtId="Maury County" active="true" lastSeen="2025-10-30T03:26:27+00:00">
    <JobTitle>25/26 School Year: Assistant Basketball Cheer Coach</JobTitle>
    <JobDescription />
    <JobType />
    <Location>Columbia, TN, USA</Location>
    <City>Columbia</City>
    <State>TN</State>
    <Country />
    <ZipCode />
    <Experience />
    <SalaryRange />
    <Benefits />
    <PostingDate>2025-08-25</PostingDate>
    <ClosingDate>Until Filled</ClosingDate>
    <JobUrl>https://mauryk12.mysmarthire.com/jobs/25194</JobUrl>
    <ApplyUrl>https://mauryk12.mysmarthire.com/jobs/25194</ApplyUrl>
    <CoachSearchUrl>https://mauryk12.mysmarthire.com/jobsearch/?job_board_classification=Coaching</CoachSearchUrl>
    <EmployerEmail />
    <EmployerFullName>Columbia, TN, USA</EmployerFullName>
    <CompanyDescription>Maury County coaching jobs</CompanyDescription>
    <CompanyEmail />
    <CompanyName>Maury County</CompanyName>
  </Job>
  <Job id="86d80616-86dd-4663-9ec1-96650433060f" state="Tennesee" district="Maury County" districtId="Maury County" active="true" lastSeen="2025-10-30T03:27:16+00:00">
    <JobTitle>25/26 School Year: Assistant Boys Basketball Coach</JobTitle>
    <JobDescription />
    <JobType />
    <Location>Mt Pleasant, TN, USA</Location>
    <City>Mt Pleasant</City>
    <State>TN</State>
    <Country />
    <ZipCode />
    <Experience />
    <SalaryRange />
    <Benefits />
    <PostingDate>2025-06-04</PostingDate>
    <ClosingDate>Until Filled</ClosingDate>
    <JobUrl>https://mauryk12.mysmarthire.com/jobs/23452</JobUrl>
    <ApplyUrl>https://mauryk12.mysmarthire.com/jobs/23452</ApplyUrl>
    <CoachSearchUrl>https://mauryk12.mysmarthire.com/jobsearch/?job_board_classification=Coaching</CoachSearchUrl>
    <EmployerEmail />
    <EmployerFullName>Mt Pleasant, TN, USA</EmployerFullName>
    <CompanyDescription>Maury County coaching jobs</CompanyDescription>
    <CompanyEmail />
    <CompanyName>Maury County</CompanyName>
  </Job>
  <Job id="ee8ecd19-1e4d-43a7-ba0e-89ac5fa4e00d" state="Tennesee" district="Maury County" districtId="Maury County" active="true" lastSeen="2025-10-30T03:28:04+00:00">
    <JobTitle>25/26 School Year: Assistant Coach: Middle School Baseball</JobTitle>
    <JobDescription />
    <JobType />
    <Location>Culleoka, TN, USA</Location>
    <City>Culleoka</City>
    <State>TN</State>
    <Country />
    <ZipCode />
    <Experience />
    <SalaryRange />
    <Benefits />
    <PostingDate>2025-07-29</PostingDate>
    <ClosingDate>Until Filled</ClosingDate>
    <JobUrl>https://mauryk12.mysmarthire.com/jobs/24767</JobUrl>
    <ApplyUrl>https://mauryk12.mysmarthire.com/jobs/24767</ApplyUrl>
    <CoachSearchUrl>https://mauryk12.mysmarthire.com/jobsearch/?job_board_classification=Coaching</CoachSearchUrl>
    <EmployerEmail />
    <EmployerFullName>Culleoka, TN, USA</EmployerFullName>
    <CompanyDescription>Maury County coaching jobs</CompanyDescription>
    <CompanyEmail />
    <CompanyName>Maury County</CompanyName>
  </Job>
  <Job id="5357add4-05ef-4e2b-b8f7-ea2096b1d0c0" state="Tennesee" district="Maury County" districtId="Maury County" active="true" lastSeen="2025-10-30T03:28:53+00:00">
    <JobTitle>25/26 School Year: Assistant Softball Coach</JobTitle>
    <JobDescription />
    <JobType />
    <Location>Spring Hill, TN, USA</Location>
    <City>Spring Hill</City>
    <State>TN</State>
    <Country />
    <ZipCode />
    <Experience />
    <SalaryRange />
    <Benefits />
    <PostingDate>2025-07-29</PostingDate>
    <ClosingDate>Until Filled</ClosingDate>
    <JobUrl>https://mauryk12.mysmarthire.com/jobs/24755</JobUrl>
    <ApplyUrl>https://mauryk12.mysmarthire.com/jobs/24755</ApplyUrl>
    <CoachSearchUrl>https://mauryk12.mysmarthire.com/jobsearch/?job_board_classification=Coaching</CoachSearchUrl>
    <EmployerEmail />
    <EmployerFullName>Spring Hill, TN, USA</EmployerFullName>
    <CompanyDescription>Maury County coaching jobs</CompanyDescription>
    <CompanyEmail />
    <CompanyName>Maury County</CompanyName>
  </Job>
  <Job id="546faff0-6abb-415c-a821-6a2ce3fe40ca" state="Tennesee" district="Maury County" districtId="Maury County" active="true" lastSeen="2025-10-30T03:29:43+00:00">
    <JobTitle>25/26 School Year: Head Tennis Coach</JobTitle>
    <JobDescription />
    <JobType />
    <Location>Spring Hill, TN, USA</Location>
    <City>Spring Hill</City>
    <State>TN</State>
    <Country />
    <ZipCode />
    <Experience />
    <SalaryRange />
    <Benefits />
    <PostingDate>2025-06-25</PostingDate>
    <ClosingDate>Until Filled</ClosingDate>
    <JobUrl>https://mauryk12.mysmarthire.com/jobs/23966</JobUrl>
    <ApplyUrl>https://mauryk12.mysmarthire.com/jobs/23966</ApplyUrl>
    <CoachSearchUrl>https://mauryk12.mysmarthire.com/jobsearch/?job_board_classification=Coaching</CoachSearchUrl>
    <EmployerEmail />
    <EmployerFullName>Spring Hill, TN, USA</EmployerFullName>
    <CompanyDescription>Maury County coaching jobs</CompanyDescription>
    <CompanyEmail />
    <CompanyName>Maury County</CompanyName>
  </Job>
  <Job id="74aa2d95-d7f9-47cf-9f83-62364101f1d8" state="Tennesee" district="Maury County" districtId="Maury County" active="true" lastSeen="2025-10-30T03:30:51+00:00">
    <JobTitle>25/26 School Year: High School Girls Basketball Assistant Coach</JobTitle>
    <JobDescription />
    <JobType />
    <Location>Hampshire, TN, USA</Location>
    <City>Hampshire</City>
    <State>TN</State>
    <Country />
    <ZipCode />
    <Experience />
    <SalaryRange />
    <Benefits />
    <PostingDate>2025-03-26</PostingDate>
    <ClosingDate>Until Filled</ClosingDate>
    <JobUrl>https://mauryk12.mysmarthire.com/jobs/21233</JobUrl>
    <ApplyUrl>https://mauryk12.mysmarthire.com/jobs/21233</ApplyUrl>
    <CoachSearchUrl>https://mauryk12.mysmarthire.com/jobsearch/?job_board_classification=Coaching</CoachSearchUrl>
    <EmployerEmail />
    <EmployerFullName>Hampshire, TN, USA</EmployerFullName>
    <CompanyDescription>Maury County coaching jobs</CompanyDescription>
    <CompanyEmail />
    <CompanyName>Maury County</CompanyName>
  </Job>
  <Job id="f997d988-06ed-4ef5-9853-c63506dba021" state="Tennesee" district="Maury County" districtId="Maury County" active="true" lastSeen="2025-10-30T03:31:57+00:00">
    <JobTitle>25/26 School Year: Softball Head Coach</JobTitle>
    <JobDescription />
    <JobType />
    <Location>Spring Hill, TN, USA</Location>
    <City>Spring Hill</City>
    <State>TN</State>
    <Country />
    <ZipCode />
    <Experience />
    <SalaryRange />
    <Benefits />
    <PostingDate>2025-05-13</PostingDate>
    <ClosingDate>Until Filled</ClosingDate>
    <JobUrl>https://mauryk12.mysmarthire.com/jobs/22488</JobUrl>
    <ApplyUrl>https://mauryk12.mysmarthire.com/jobs/22488</ApplyUrl>
    <CoachSearchUrl>https://mauryk12.mysmarthire.com/jobsearch/?job_board_classification=Coaching</CoachSearchUrl>
    <EmployerEmail />
    <EmployerFullName>Spring Hill, TN, USA</EmployerFullName>
    <CompanyDescription>Maury County coaching jobs</CompanyDescription>
    <CompanyEmail />
    <CompanyName>Maury County</CompanyName>
  </Job>
  <Job id="8d6b02d7-8bbf-4a70-a0eb-a8b11bea06e1" state="Tennesee" district="Maury County" districtId="Maury County" active="true" lastSeen="2025-10-30T03:33:07+00:00">
    <JobTitle>Assistant Boys Soccer Coach</JobTitle>
    <JobDescription />
    <JobType />
    <Location>Columbia, TN, USA</Location>
    <City>Columbia</City>
    <State>TN</State>
    <Country />
    <ZipCode />
    <Experience />
    <SalaryRange />
    <Benefits />
    <PostingDate>2025-10-03</PostingDate>
    <ClosingDate>Until Filled</ClosingDate>
    <JobUrl>https://mauryk12.mysmarthire.com/jobs/25728</JobUrl>
    <ApplyUrl>https://mauryk12.mysmarthire.com/jobs/25728</ApplyUrl>
    <CoachSearchUrl>https://mauryk12.mysmarthire.com/jobsearch/?job_board_classification=Coaching</CoachSearchUrl>
    <EmployerEmail />
    <EmployerFullName>Columbia, TN, USA</EmployerFullName>
    <CompanyDescription>Maury County coaching jobs</CompanyDescription>
    <CompanyEmail />
    <CompanyName>Maury County</CompanyName>
  </Job>
  <Job id="6bce4848-16f5-49ae-8b78-7d1c6197a7c7" state="Tennesee" district="Maury County" districtId="Maury County" active="true" lastSeen="2025-10-30T03:34:20+00:00">
    <JobTitle>Assistant Boys Soccer Coach</JobTitle>
    <JobDescription />
    <JobType />
    <Location>Columbia, TN, USA</Location>
    <City>Columbia</City>
    <State>TN</State>
    <Country />
    <ZipCode />
    <Experience />
    <SalaryRange />
    <Benefits />
    <PostingDate>2025-10-17</PostingDate>
    <ClosingDate>Until Filled</ClosingDate>
    <JobUrl>https://mauryk12.mysmarthire.com/jobs/25853</JobUrl>
    <ApplyUrl>https://mauryk12.mysmarthire.com/jobs/25853</ApplyUrl>
    <CoachSearchUrl>https://mauryk12.mysmarthire.com/jobsearch/?job_board_classification=Coaching</CoachSearchUrl>
    <EmployerEmail />
    <EmployerFullName>Columbia, TN, USA</EmployerFullName>
    <CompanyDescription>Maury County coaching jobs</CompanyDescription>
    <CompanyEmail />
    <CompanyName>Maury County</CompanyName>
  </Job>
  <Job id="a14d53de-4d4a-4cd3-b4af-cdb00e4f4d38" state="Tennesee" district="Maury County" districtId="Maury County" active="true" lastSeen="2025-10-30T03:35:34+00:00">
    <JobTitle>Assistant Girls Basketball Coach</JobTitle>
    <JobDescription />
    <JobType />
    <Location>Columbia, TN, USA</Location>
    <City>Columbia</City>
    <State>TN</State>
    <Country />
    <ZipCode />
    <Experience />
    <SalaryRange />
    <Benefits />
    <PostingDate>2025-10-24</PostingDate>
    <ClosingDate>Until Filled</ClosingDate>
    <JobUrl>https://mauryk12.mysmarthire.com/jobs/25955</JobUrl>
    <ApplyUrl>https://mauryk12.mysmarthire.com/jobs/25955</ApplyUrl>
    <CoachSearchUrl>https://mauryk12.mysmarthire.com/jobsearch/?job_board_classification=Coaching</CoachSearchUrl>
    <EmployerEmail />
    <EmployerFullName>Columbia, TN, USA</EmployerFullName>
    <CompanyDescription>Maury County coaching jobs</CompanyDescription>
    <CompanyEmail />
    <CompanyName>Maury County</CompanyName>
  </Job>
  <Job id="6e285b98-30e5-4e74-8712-253086434a53" state="Tennesee" district="Maury County" districtId="Maury County" active="true" lastSeen="2025-10-30T03:37:11+00:00">
    <JobTitle>Assistant Girls Flag Football Coach</JobTitle>
    <JobDescription />
    <JobType />
    <Location>Columbia, TN, USA</Location>
    <City>Columbia</City>
    <State>TN</State>
    <Country />
    <ZipCode />
    <Experience />
    <SalaryRange />
    <Benefits />
    <PostingDate>2025-10-17</PostingDate>
    <ClosingDate>Until Filled</ClosingDate>
    <JobUrl>https://mauryk12.mysmarthire.com/jobs/25851</JobUrl>
    <ApplyUrl>https://mauryk12.mysmarthire.com/jobs/25851</ApplyUrl>
    <CoachSearchUrl>https://mauryk12.mysmarthire.com/jobsearch/?job_board_classification=Coaching</CoachSearchUrl>
    <EmployerEmail />
    <EmployerFullName>Columbia, TN, USA</EmployerFullName>
    <CompanyDescription>Maury County coaching jobs</CompanyDescription>
    <CompanyEmail />
    <CompanyName>Maury County</CompanyName>
  </Job>
  <Job id="e26475f8-231c-4899-ab94-34c13521b665" state="Tennesee" district="Maury County" districtId="Maury County" active="true" lastSeen="2025-10-30T03:38:58+00:00">
    <JobTitle>Assistant Girls Flag Football Coach</JobTitle>
    <JobDescription />
    <JobType />
    <Location>Columbia, TN, USA</Location>
    <City>Columbia</City>
    <State>TN</State>
    <Country />
    <ZipCode />
    <Experience />
    <SalaryRange />
    <Benefits />
    <PostingDate>2025-10-17</PostingDate>
    <ClosingDate>Until Filled</ClosingDate>
    <JobUrl>https://mauryk12.mysmarthire.com/jobs/25852</JobUrl>
    <ApplyUrl>https://mauryk12.mysmarthire.com/jobs/25852</ApplyUrl>
    <CoachSearchUrl>https://mauryk12.mysmarthire.com/jobsearch/?job_board_classification=Coaching</CoachSearchUrl>
    <EmployerEmail />
    <EmployerFullName>Columbia, TN, USA</EmployerFullName>
    <CompanyDescription>Maury County coaching jobs</CompanyDescription>
    <CompanyEmail />
    <CompanyName>Maury County</CompanyName>
  </Job>
  <Job id="28f16ce6-aa50-4245-9780-67fd42a934e2" state="Tennesee" district="Maury County" districtId="Maury County" active="true" lastSeen="2025-10-30T03:40:43+00:00">
    <JobTitle>Assistant Soccer Coach</JobTitle>
    <JobDescription />
    <JobType />
    <Location>Spring Hill, TN, USA</Location>
    <City>Spring Hill</City>
    <State>TN</State>
    <Country />
    <ZipCode />
    <Experience />
    <SalaryRange />
    <Benefits />
    <PostingDate>2025-10-13</PostingDate>
    <ClosingDate>Until Filled</ClosingDate>
    <JobUrl>https://mauryk12.mysmarthire.com/jobs/25793</JobUrl>
    <ApplyUrl>https://mauryk12.mysmarthire.com/jobs/25793</ApplyUrl>
    <CoachSearchUrl>https://mauryk12.mysmarthire.com/jobsearch/?job_board_classification=Coaching</CoachSearchUrl>
    <EmployerEmail />
    <EmployerFullName>Spring Hill, TN, USA</EmployerFullName>
    <CompanyDescription>Maury County coaching jobs</CompanyDescription>
    <CompanyEmail />
    <CompanyName>Maury County</CompanyName>
  </Job>
  <Job id="bc184464-c92c-465f-9d64-1f80035796ee" state="Tennesee" district="Bradley County" districtId="Bradley County" active="true" lastSeen="2025-10-30T03:41:01+00:00">
    <JobTitle>After-School Program Instructional Coach - Part-Time - Interim</JobTitle>
    <JobDescription />
    <JobType />
    <Location>Big City University</Location>
    <City />
    <State>TN</State>
    <Country />
    <ZipCode />
    <Experience />
    <SalaryRange />
    <Benefits />
    <PostingDate>2025-05-28</PostingDate>
    <ClosingDate />
    <JobUrl>https://www.applitrack.com/Bradleyschools/onlineapp/jobpostings/view.asp?AppliTrackPostingSearch=title%3Acoach%20&amp;AppliTrackZipRadius=5&amp;AppliTrackLayoutMode=detail</JobUrl>
    <ApplyUrl>https://www.applitrack.com/Bradleyschools/onlineapp/jobpostings/view.asp?AppliTrackPostingSearch=title%3Acoach%20&amp;AppliTrackZipRadius=5&amp;AppliTrackLayoutMode=detail</ApplyUrl>
    <CoachSearchUrl>https://www.applitrack.com/Bradleyschools/onlineapp/jobpostings/view.asp?AppliTrackPostingSearch=title%3Acoach%20&amp;AppliTrackZipRadius=5&amp;AppliTrackLayoutMode=detail</CoachSearchUrl>
    <EmployerEmail />
    <EmployerFullName>Big City University</EmployerFullName>
    <CompanyDescription>Bradley County coaching jobs</CompanyDescription>
    <CompanyEmail />
    <CompanyName>Bradley County</CompanyName>
  </Job>
  <Job id="1f48395b-1250-465e-abac-5971941908b4" state="Tennesee" district="Blount County" districtId="Blount County" active="true" lastSeen="2025-10-30T03:41:24+00:00">
    <JobTitle>Softball Coach 2024-2025</JobTitle>
    <JobDescription />
    <JobType />
    <Location>William Blount High School</Location>
    <City />
    <State>TN</State>
    <Country />
    <ZipCode />
    <Experience />
    <SalaryRange />
    <Benefits />
    <PostingDate>2024-04-30</PostingDate>
    <ClosingDate>2024-05-30</ClosingDate>
    <JobUrl>https://www.applitrack.com/Blountk12/onlineapp/default.aspx?AppliTrackPostingSearch=coach</JobUrl>
    <ApplyUrl>https://www.applitrack.com/Blountk12/onlineapp/default.aspx?AppliTrackPostingSearch=coach</ApplyUrl>
    <CoachSearchUrl>https://www.applitrack.com/Blountk12/onlineapp/default.aspx?AppliTrackPostingSearch=coach</CoachSearchUrl>
    <EmployerEmail />
    <EmployerFullName>William Blount High School</EmployerFullName>
    <CompanyDescription>Blount County coaching jobs</CompanyDescription>
    <CompanyEmail />
    <CompanyName>Blount County</CompanyName>
  </Job>
  <Job id="4c32fbc2-9978-41da-815c-03a06759e771" state="Tennesee" district="Bedford County" districtId="Bedford County" active="true" lastSeen="2025-10-30T03:42:22+00:00">
    <JobTitle>Coach Head Football - 2026/2027 Season (6th-8th Grade) - Liberty School</JobTitle>
    <JobDescription />
    <JobType />
    <Location>Shelbyville, TN, USA</Location>
    <City>Shelbyville</City>
    <State>TN</State>
    <Country />
    <ZipCode />
    <Experience />
    <SalaryRange />
    <Benefits />
    <PostingDate>2025-10-08</PostingDate>
    <ClosingDate />
    <JobUrl>https://bedfordk12tn.mysmarthire.com/jobs/25766</JobUrl>
    <ApplyUrl>https://bedfordk12tn.mysmarthire.com/jobs/25766</ApplyUrl>
    <CoachSearchUrl>https://bedfordk12tn.mysmarthire.com/jobs/</CoachSearchUrl>
    <EmployerEmail />
    <EmployerFullName>Bedford County</EmployerFullName>
    <CompanyDescription>Bedford County coaching jobs</CompanyDescription>
    <CompanyEmail />
    <CompanyName>Bedford County</CompanyName>
  </Job>
</Jobs>
